<?xml version="1.0" encoding="utf-8"?>
<MultiPowUpload_parameters>
  <param name="browseButton.text">Pasco ...</param>
  <param name="browseButton.tooltip">Addere lima enim upload</param>
  <param name="cancelButton.pauseText">Mora</param>
  <param name="cancelButton.text">Inrita</param>
  <param name="cancelButton.tooltip">Inrita current operatio</param>
  <param name="clearButton.text">Purgare</param>
  <param name="clearButton.tooltip">Omnem lima</param>
  <param name="constant.bytes">bytes</param>
  <param name="constant.decimalSeparator">,</param>
  <param name="constant.gigaBytes">GB</param>
  <param name="constant.kiloBytes">Kb</param>
  <param name="constant.megaBytes">Mb</param>
  <param name="contextMenu.sortByDate">Modi per date</param>
  <param name="contextMenu.sortByName">Modi per nomen</param>
  <param name="contextMenu.sortBySize">Modi per mole</param>
  <param name="descriptionWindow.caption">Descriptio enim file</param>
  <param name="descriptionWindow.fileNavigation.fileName.label">&lt;FILENAME&gt;</param>
  <param name="descriptionWindow.fileNavigation.nextButton.label"></param>
  <param name="descriptionWindow.fileNavigation.previousButton.label"></param>
  <param name="exifWindow.caption">&lt;FILENAME&gt; Exif notitia</param>
  <param name="exifWindow.list.nameHeader">Nomen</param>
  <param name="exifWindow.list.valueHeader">Valor</param>
  <param name="fileInfoWindow.caption">File notitia</param>
  <param name="fileInfoWindow.exifInfo">&lt;b&gt;Exif info&lt;/b&gt;: &lt;a&gt;Click to view&lt;/a&gt;</param>
  <param name="fileInfoWindow.fileDate">&lt;b&gt;Date&lt;/b&gt;: &lt;FILEDATE&gt;</param>
  <param name="fileInfoWindow.fileName">&lt;b&gt;Name&lt;/b&gt;: &lt;FILENAME&gt;</param>
  <param name="fileInfoWindow.fileSize">&lt;b&gt;Size&lt;/b&gt;: &lt;FILESIZE&gt;</param>
  <param name="fileInfoWindow.fileStatus">&lt;b&gt;Status&lt;/b&gt;: &lt;FILESTATUS&gt;</param>
  <param name="fileInfoWindow.imageHeight">&lt;b&gt;Image height&lt;/b&gt;: &lt;IMAGEHEIGHT&gt;</param>
  <param name="fileInfoWindow.imageWidth">&lt;b&gt;Image width&lt;/b&gt;: &lt;IMAGEWIDTH&gt;</param>
  <param name="fileStatus.cancelled">EXPUNCTUS</param>
  <param name="fileStatus.complete">Completur</param>
  <param name="fileStatus.encodeImage">Encode imaginem</param>
  <param name="fileStatus.error">Error occurrit</param>
  <param name="fileStatus.loadFile">Oneratisque file in memoria</param>
  <param name="fileStatus.loadImage">Oneratisque imaginem notitia</param>
  <param name="fileStatus.processing">Uploading</param>
  <param name="fileStatus.ready">Parati</param>
  <param name="fileView.fileDownload.tooltip">Download file</param>
  <param name="imageEditWindow.caption">Creare imaginem</param>
  <param name="labelUpload.text">Lego Lima ut upload</param>
  <param name="listView.description.defaultText">Click ad creare ...</param>
  <param name="listView.description.tooltip">Creare file description</param>
  <param name="listView.fileNameLabel.pattern">&lt;FILENAME&gt;</param>
  <param name="listView.label.disabledFileInfoTooltip">Magnitudine: &lt;FILESIZE&gt;
Date: &lt;FILEDATE&gt;
Status: &lt;FILESTATUS&gt;</param>
  <param name="listView.label.tooltip">Magnitudine: &lt;FILESIZE&gt;
Date: &lt;FILEDATE&gt;
Status: &lt;FILESTATUS&gt;</param>
  <param name="listView.removeButton.tooltip">Tollere file</param>
  <param name="listView.textInput.defaultString">Scribere lima comment hic</param>
  <param name="listViewButton.tooltip">Album visum</param>
  <param name="loadingText">&lt;b&gt;INITIALIZING: &lt;PERCENT&gt;% &lt;/b&gt;</param>
  <param name="messages.disabledType">File with following types : &lt;FILETYPES&gt; are not allowed to upload! &lt;COUNTINVALIDFILES&gt; files were ignored!</param>
  <param name="messages.errorLoadingRemoteFiles">Non oneratis remota lima album. &lt;ERROR&gt;</param>
  <param name="messages.fileSizeExceeded">Only files less than &lt;MAXFILESIZE&gt; are allowed. &lt;COUNTINVALIDFILES&gt; files were ignored!</param>
  <param name="messages.fileSizeNotEnough">Only files more than &lt;MINFILESIZE&gt; are allowed. &lt;COUNTINVALIDFILES&gt; files were ignored!</param>
  <param name="messages.fileTooBigForUpload">File magnitudine est nimium enim upload. Suspendisse file cum minus magnitudine.</param>
  <param name="messages.fileTooBigForUpload">File magnitudine est nimium enim upload. Suspendisse file cum minus magnitudine.</param>
  <param name="messages.filesCountExceeded">Only &lt;MAXFILECOUNT&gt; files allowed to upload! &lt;COUNTINVALIDFILES&gt; files were ignored!</param>
  <param name="messages.filesCountNotEnough">Placere lego magis lima. Minimum lima numerare est &lt;MINFILECOUNT&gt;</param>
  <param name="messages.httpError">&lt;center&gt;HTTP Error, '&lt;ERRORCODE&gt;' occurred. &lt;DESCRIPTION&gt; &lt;br&gt; Please see &lt;font color='#0000FF'&gt;&lt;a title='Error description' target='_blank' href='&lt;W3WLINK&gt;'&gt;&lt;W3WLINK&gt;&lt;/a&gt;&lt;/font&gt; error code definitions for more information. &lt;/center&gt;</param>
  <param name="messages.httpError.400">Malum Request. Cultor potest non intelligere petentibus! Placere contactus tua server administrator.</param>
  <param name="messages.httpError.401">Alienum. User authenticas requiritur!</param>
  <param name="messages.httpError.402">Solutione dictum. Reservatur codicem!</param>
  <param name="messages.httpError.403">Prohibetur. In server intelligi instantiam, sed negat ad illud!&lt;br&gt;Enim apache servientibus: hoc fit quia enabled an Apache moduli nomine mod_security in server praecludit in Caput capitis misit per Flash.&lt;br&gt;Pro IIS cum ASP servientibus: hoc exitus occurrit si a Content-Length caput est et si Content-Length caput specificat moles notitia quod est maior quam valor AspMaxRequestEntityAllowed proprietas in in IIS metabase.&lt;br&gt;In default valorem AspMaxRequestEntityAllowed proprietas est 204.800 bytes.</param>
  <param name="messages.httpError.404">Pagina non. Potest non '&lt;URL&gt;' page in server!</param>
  <param name="messages.httpError.405">Stipes modus non liceat hoc page &lt;URL&gt;! Aliquam mutare server occasus ad patitur post modus recieving script.</param>
  <param name="messages.httpError.406">Non Jucundus. Hoc quod server potest non generare responsio entia quae contentus characteres non accepta secundum ad accipere Caput capitis misit in precibus. Flash accipere caput est 'text / *'.</param>
  <param name="messages.httpError.407">Procuratorem AUCTORITAS dictum.</param>
  <param name="messages.httpError.408">Petentibus Timeout.</param>
  <param name="messages.httpError.409">Certamen.</param>
  <param name="messages.httpError.410">Abiit. Rogatus resource est non available in server et non procuret inscriptio est notum.</param>
  <param name="messages.httpError.411">Tandem dictum.</param>
  <param name="messages.httpError.412">Precondition Deficio.</param>
  <param name="messages.httpError.413">Petitionem Entitate Nimis Large.&lt;br&gt;Pro IIS servientibus: I. Conantur crescere UploadReadAheadSize metabase proprietas.&lt;br&gt;II. Conantur crescere MaxRequestEntityAllowed bonis valorem in IIS config.&lt;br&gt;Enim apache servientibus: Conare crescere LimitRequestBody parameter in httpd.conf.</param>
  <param name="messages.httpError.414">Precibus-URI diu.</param>
  <param name="messages.httpError.415">Adfligunt Media Type.</param>
  <param name="messages.httpError.416">Postulavit dolor Non Satisfiable.</param>
  <param name="messages.httpError.417">Expectatio Deficio.</param>
  <param name="messages.httpError.500">Interno Server Error. Solet quod accepto script habent errores.</param>
  <param name="messages.httpError.501">Non implemented. Cultor non sustinere POST modus.</param>
  <param name="messages.httpError.502">Malum porta.</param>
  <param name="messages.httpError.503">DIII ipsum Unavailable. In server est currently non tractare petitionem debitum ad temporaria obruuntur vel sustentacionem server.</param>
  <param name="messages.httpError.504">Porta Timeout.</param>
  <param name="messages.httpError.505">HTTP Version Non suffulti. Cultor non sustinere HTTP 1.1.</param>
  <param name="messages.invalidImageDimension">Image should satisfy the following conditions :  width is from &lt;MINWIDTH&gt; to &lt;MAXWIDTH&gt; pixels &lt;br&gt; height is from &lt;MINHEIGHT&gt; to &lt;MAXHEIGHT&gt; pixels.&lt;br&gt; &lt;COUNTINVALIDFILES&gt; lima sunt neglecta!</param>
  <param name="messages.missingRequiredField">The value of required field '&lt;FIELDNAME&gt;' is missing for file &lt;FILENAME&gt;!</param>
  <param name="messages.onlyOneBrowseDialogAllowed">Pasco alternis iam aperuit. Unum file pasco session ut fieri ad tempus.</param>
  <param name="messages.onlyOneBrowseDialogAllowed">Pasco alternis iam aperuit. Unum file pasco session ut fieri ad tempus.</param>
  <param name="messages.selectFewer">Improviso error dum questus delectis lima album. Aliquam lego pauciores lima.</param>
  <param name="messages.wrongFileType">Only files with following type: &lt;FILETYPES&gt; allowed to upload! &lt;COUNTINVALIDFILES&gt; files were ignored!</param>
  <param name="messages.zeroSize">&lt;COUNTINVALIDFILES&gt; lima cum nulla magnitudine sunt neglecta!</param>
  <param name="removeButton.tooltip">Tollere delectis lima</param>
  <param name="retryDialog.caption">Retry upload?</param>
  <param name="retryDialog.message">Quidam lima sunt non purus. Visne iterum temptare felis?</param>
  <param name="retryDialog.noLabel">Non</param>
  <param name="retryDialog.yesLabel">Sic</param>
  <param name="sortButton.text"></param>
  <param name="sortButton.tooltip">Diribitio ordinem</param>
  <param name="sortMenu.byDate">Per date</param>
  <param name="sortMenu.byName">Per nomen</param>
  <param name="sortMenu.bySize">A magnitudine</param>
  <param name="statusLabel.text.downloadComplete">Download complete! Elapsed time: &lt;ELAPSEDHOUR&gt;:&lt;ELAPSEDMIN&gt;:&lt;ELAPSEDSEC&gt;</param>
  <param name="statusLabel.text.generateThumbnails">Generandi imaginem thumbnails ... placet expectare.</param>
  <param name="statusLabel.text.loadFile "></param>
  <param name="statusLabel.text.ready">Count of files: &lt;FILESCOUNT&gt; (&lt;TOTALSIZE&gt;)</param>
  <param name="statusLabel.text.uploadCancelled">Deinde lima upload cassari. Expectare ...</param>
  <param name="statusLabel.text.uploadComplete">Upload complete! &lt;UPLOADEDFILESCOUNT&gt; files (&lt;TOTALUPLOADEDSIZE&gt;/&lt;TOTALUPLOADSIZE&gt;), Elapsed time: &lt;ELAPSEDHOUR&gt;:&lt;ELAPSEDMIN&gt;:&lt;ELAPSEDSEC&gt;</param>
  <param name="statusLabel.text.uploadProgress">Total: &lt;PERCENT&gt;% (&lt;FILESNUM&gt;/&lt;FILESTOUPLOADCOUNT&gt;) &lt;TOTALUPLOADEDSIZE&gt;/&lt;TOTALUPLOADSIZE&gt; (&lt;RATEVALUE&gt;/sec, time left: &lt;LEFTHOUR&gt;:&lt;LEFTMIN&gt;:&lt;LEFTSEC&gt;)</param>
  <param name="statusLabel.text.uploadStart">Uploading ...</param>
  <param name="statusLabel.text.uploadStopped">Upload stopped. Uploaded bytes: &lt;TOTALUPLOADEDSIZE&gt;, Elapsed time: &lt;ELAPSEDHOUR&gt;:&lt;ELAPSEDMIN&gt;:&lt;ELAPSEDSEC&gt;</param>
  <param name="statusLabel.text.waitForConnection">Cultor non respondere. Conatur vestibulum, placet expectare.</param>
  <param name="thumbViewButton.tooltip">Thumbnails considerandam</param>
  <param name="thumbnail.watermark.text">Elementum-IT</param>
  <param name="thumbnailView.bottomPanel.labelPattern">&lt;FILENAME&gt;</param>
  <param name="thumbnailView.cancelCropIcon.tooltip">Abrogare carpent imaginem</param>
  <param name="thumbnailView.contextMenu.CropLabel">Carpent imaginem</param>
  <param name="thumbnailView.contextMenu.RemoveLabel">Tollere</param>
  <param name="thumbnailView.contextMenu.RotateLeftLabel">Gyrari reliquit</param>
  <param name="thumbnailView.contextMenu.RotateRightLabel">Gyrari ius</param>
  <param name="thumbnailView.contextMenu.UndoCropLabel">Abrogare carpent imaginem</param>
  <param name="thumbnailView.cropIcon.tooltip">Carpent imaginem</param>
  <param name="thumbnailView.editIcon.tooltip">Creare file description</param>
  <param name="thumbnailView.editImgIcon.tooltip">Duis imaginem</param>
  <param name="thumbnailView.infoIcon.disabledFileInfoTooltip">Magnitudine: &lt;FILESIZE&gt;
Date: &lt;FILEDATE&gt;
Status: &lt;FILESTATUS&gt;</param>
  <param name="thumbnailView.infoIcon.tooltip">Magnitudine: &lt;FILESIZE&gt;
Date: &lt;FILEDATE&gt;
Status: &lt;FILESTATUS&gt;</param>
  <param name="thumbnailView.removeIcon.tooltip">Tollere</param>
  <param name="thumbnailView.rotateLeftIcon.tooltip">Gyrari reliquit</param>
  <param name="thumbnailView.rotateRightIcon.tooltip">Gyrari ius</param>
  <param name="uploadButton.text">Upload</param>
  <param name="uploadButton.tooltip">Committitur upload</param>
  <param name="window.errorCaption">Errorem</param>
  <param name="window.warningCaption">Admonitio</param>
</MultiPowUpload_parameters>